conndoc/__init__.py
conndoc/cli.py
conndoc/constants.py
conndoc/utils.py
conndoc/validators.py
conndoc-0.2.2.dist-info/LICENSE
conndoc-0.2.2.dist-info/METADATA
conndoc-0.2.2.dist-info/WHEEL
conndoc-0.2.2.dist-info/entry_points.txt
conndoc-0.2.2.dist-info/RECORD
